Metadata-Version: 2.1
Name: pretermgrowth
Version: 0.3
Summary: Calculate growth measurement z-scores for preterm infants
Home-page: UNKNOWN
Author: Matt Devine
Author-email: mddevine@gmail.com
License: UNKNOWN
Download-URL: https://github.com/gammaflauge/pretermgrowth/archive/v0.3.tar.gz
Project-URL: Source Code, https://github.com/gammaflauge/pretermgrowth/
Keywords: preterm neonatology fenton growth
Platform: UNKNOWN
Requires-Python: >=3.6
